{
  "nombre": "Crime Patrol",
  "nombre_original": "Crime Patrol",
  "sistema": "American Laser Games",
  "year": "1993",
  "genres": [
    "Gun"
  ],
  "publisher": "American Laser Games",
  "aiDescription": "Crime Patrol, lanzado por American Laser Games en 1993, nos sumerge en el papel de un agente de policía novato que asciende de rango. Este título pionero de disparos con pistola de luz se distingue por su innovador uso de video de movimiento completo (FMV) con actores reales. Los jugadores deben reaccionar rápidamente para abatir a los criminales que aparecen en pantalla, evitando a toda costa herir a civiles inocentes. La mecánica es sencilla: apuntar y disparar, gestionando la munición y recargando fuera de la pantalla, lo que exige reflejos agudos y precisión milimétrica.Este juego es un testimonio fascinante de la era dorada de los títulos FMV, una tendencia que buscaba fusionar el cine con la interactividad. Aunque hoy pueda parecer rudimentario, en su momento, Crime Patrol ofreció una experiencia inmersiva y novedosa, capitalizando la emoción de participar en una película interactiva. Su legado reside en su capacidad para transportarnos a un momento de experimentación audaz en la industria de los videojuegos, consolidándose como una pieza nostálgica y culturalmente significativa de su época.",
  "aiHints": "¿Sabías que...- American Laser Games filmó Crime Patrol y la mayoría de sus juegos en Albuquerque, Nuevo México, utilizando a menudo talentos locales de la comunidad. Esto le dio a sus producciones un encanto particular de película de serie B.- La dificultad del juego era legendaria, con enemigos que aparecían y desaparecían en fracciones de segundo, poniendo a prueba incluso a los tiradores más experimentados.- El juego utilizaba un reproductor de LaserDisc en sus versiones de arcade, lo que permitía la alta calidad de video para su época, una verdadera proeza tecnológica.",
  "tiene_review": false
}